get_chrome_paths.py
get_chrome_paths-0.1.1.dist-info/licenses/LICENSE
get_chrome_paths-0.1.1.dist-info/METADATA
get_chrome_paths-0.1.1.dist-info/WHEEL
get_chrome_paths-0.1.1.dist-info/top_level.txt
get_chrome_paths-0.1.1.dist-info/RECORD
