Metadata-Version: 2.4
Name: get-chrome-paths
Version: 0.1.1
Summary: A cross-platform Python utility to find Chromium-based browser executable paths on Windows, macOS, and Linux.
Author-email: Jifeng Wu <jifengwu2k@gmail.com>
License-Expression: MIT
Project-URL: Homepage, https://github.com/jifengwu2k/get-chrome-paths
Project-URL: Bug Tracker, https://github.com/jifengwu2k/get-chrome-paths/issues
Classifier: Programming Language :: Python :: 2
Classifier: Programming Language :: Python :: 3
Classifier: Operating System :: OS Independent
Requires-Python: >=2
License-File: LICENSE
Dynamic: license-file
